MANIFEST.in
README.rst
setup.py
django_longform.egg-info/PKG-INFO
django_longform.egg-info/SOURCES.txt
django_longform.egg-info/dependency_links.txt
django_longform.egg-info/requires.txt
django_longform.egg-info/top_level.txt
longform/__init__.py
longform/admin.py
longform/feeds.py
longform/models.py
longform/tests.py
longform/urls.py
longform/views.py