Metadata-Version: 1.0
Name: django-longform
Version: 0.2.0
Summary: A Django application for longform blogging.
Home-page: https://github.com/martey/django-longform
Author: Martey Dodoo
Author-email: django-longform@marteydodoo.com
License: MIT
Platform: UNKNOWN
